setup.py
periapt/__init__.py
periapt/apt.py
periapt/dpkg.py
periapt/main.py
periapt/util.py
periapt/version.py
periapt.egg-info/PKG-INFO
periapt.egg-info/SOURCES.txt
periapt.egg-info/dependency_links.txt
periapt.egg-info/entry_points.txt
periapt.egg-info/top_level.txt